{"otherData": {},"traceEvents":[{},{"cat":"function","dur":160239,"name":"glfwInit","ph":"X","pid":0,"tid":7944,"ts":1464614353621.100},{"cat":"function","dur":284609,"name":"glfwCreateWindow","ph":"X","pid":0,"tid":7944,"ts":1464614514165.200},{"cat":"function","dur":2397,"name":"void Hazel::OpenGLContext::Init(void)","ph":"X","pid":0,"tid":7944,"ts":1464614798994.000},{"cat":"function","dur":14,"name":"void Hazel::WindowsWindow::SetVSync(bool)","ph":"X","pid":0,"tid":7944,"ts":1464614801497.600},{"cat":"function","dur":448985,"name":"void Hazel::WindowsWindow::Init(const struct Hazel::WindowProps &)","ph":"X","pid":0,"tid":7944,"ts":1464614352580.400},{"cat":"function","dur":449026,"name":"Hazel::WindowsWindow::WindowsWindow(const struct Hazel::WindowProps &)","ph":"X","pid":0,"tid":7944,"ts":1464614352576.400},{"cat":"function","dur":23,"name":"void Hazel::OpenGLRendererAPI::Init(void)","ph":"X","pid":0,"tid":7944,"ts":1464614801672.700},{"cat":"function","dur":26,"name":"Hazel::OpenGLVertexArray::OpenGLVertexArray(void)","ph":"X","pid":0,"tid":7944,"ts":1464614801768.000},{"cat":"function","dur":374,"name":"Hazel::OpenGLVertexBuffer::OpenGLVertexBuffer(unsigned int)","ph":"X","pid":0,"tid":7944,"ts":1464614801870.300},{"cat":"function","dur":1,"name":"void Hazel::OpenGLVertexBuffer::Bind(void) const","ph":"X","pid":0,"tid":7944,"ts":1464614802430.900},{"cat":"function","dur":107,"name":"void Hazel::OpenGLVertexArray::AddVertexBuffer(const class std::shared_ptr<class Hazel::VertexBuffer> &)","ph":"X","pid":0,"tid":7944,"ts":1464614802400.700},{"cat":"function","dur":732,"name":"Hazel::OpenGLIndexBuffer::OpenGLIndexBuffer(unsigned int *,unsigned int)","ph":"X","pid":0,"tid":7944,"ts":1464614803394.900},{"cat":"function","dur":1,"name":"void Hazel::OpenGLIndexBuffer::Bind(void) const","ph":"X","pid":0,"tid":7944,"ts":1464614804215.800},{"cat":"function","dur":54,"name":"void Hazel::OpenGLVertexArray::SetIndexBuffer(const class std::shared_ptr<class Hazel::IndexBuffer> &)","ph":"X","pid":0,"tid":7944,"ts":1464614804201.400},{"cat":"function","dur":4,"name":"Hazel::OpenGLVertexArray::OpenGLVertexArray(void)","ph":"X","pid":0,"tid":7944,"ts":1464614804301.800},{"cat":"function","dur":100,"name":"Hazel::OpenGLVertexBuffer::OpenGLVertexBuffer(unsigned int)","ph":"X","pid":0,"tid":7944,"ts":1464614804344.700},{"cat":"function","dur":0,"name":"void Hazel::OpenGLVertexBuffer::Bind(void) const","ph":"X","pid":0,"tid":7944,"ts":1464614804551.100},{"cat":"function","dur":60,"name":"void Hazel::OpenGLVertexArray::AddVertexBuffer(const class std::shared_ptr<class Hazel::VertexBuffer> &)","ph":"X","pid":0,"tid":7944,"ts":1464614804536.400},{"cat":"function","dur":1,"name":"void Hazel::OpenGLIndexBuffer::Bind(void) const","ph":"X","pid":0,"tid":7944,"ts":1464614804632.600},{"cat":"function","dur":35,"name":"void Hazel::OpenGLVertexArray::SetIndexBuffer(const class std::shared_ptr<class Hazel::IndexBuffer> &)","ph":"X","pid":0,"tid":7944,"ts":1464614804632.100},{"cat":"function","dur":4,"name":"Hazel::OpenGLVertexArray::OpenGLVertexArray(void)","ph":"X","pid":0,"tid":7944,"ts":1464614805711.200},{"cat":"function","dur":1502,"name":"Hazel::OpenGLVertexBuffer::OpenGLVertexBuffer(unsigned int)","ph":"X","pid":0,"tid":7944,"ts":1464614805764.400},{"cat":"function","dur":1,"name":"void Hazel::OpenGLVertexBuffer::Bind(void) const","ph":"X","pid":0,"tid":7944,"ts":1464614807363.600},{"cat":"function","dur":56,"name":"void Hazel::OpenGLVertexArray::AddVertexBuffer(const class std::shared_ptr<class Hazel::VertexBuffer> &)","ph":"X","pid":0,"tid":7944,"ts":1464614807352.900},{"cat":"function","dur":187,"name":"Hazel::OpenGLTexture2D::OpenGLTexture2D(unsigned int,unsigned int)","ph":"X","pid":0,"tid":7944,"ts":1464614807998.800},{"cat":"function","dur":395,"name":"void Hazel::OpenGLTexture2D::SetData(void *,unsigned int)","ph":"X","pid":0,"tid":7944,"ts":1464614808257.600},{"cat":"function","dur":177,"name":"class std::basic_string<char,struct std::char_traits<char>,class std::allocator<char> > Hazel::OpenGLShader::ReadFile(const class std::basic_string<char,struct std::char_traits<char>,class std::allocator<char> > &)","ph":"X","pid":0,"tid":7944,"ts":1464614809003.400},{"cat":"function","dur":106,"name":"class std::unordered_map<unsigned int,class std::basic_string<char,struct std::char_traits<char>,class std::allocator<char> >,struct std::hash<unsigned int>,struct std::equal_to<unsigned int>,class std::allocator<struct std::pair<unsigned int const ,class std::basic_string<char,struct std::char_traits<char>,class std::allocator<char> > > > > Hazel::OpenGLShader::PreProcess(const class std::basic_string<char,struct std::char_traits<char>,class std::allocator<char> > &)","ph":"X","pid":0,"tid":7944,"ts":1464614809306.000},{"cat":"function","dur":14096,"name":"Hazel::OpenGLShader::OpenGLShader(const class std::basic_string<char,struct std::char_traits<char>,class std::allocator<char> > &)","ph":"X","pid":0,"tid":7944,"ts":1464614808875.600},{"cat":"function","dur":140,"name":"class std::basic_string<char,struct std::char_traits<char>,class std::allocator<char> > Hazel::OpenGLShader::ReadFile(const class std::basic_string<char,struct std::char_traits<char>,class std::allocator<char> > &)","ph":"X","pid":0,"tid":7944,"ts":1464614823154.600},{"cat":"function","dur":42,"name":"class std::unordered_map<unsigned int,class std::basic_string<char,struct std::char_traits<char>,class std::allocator<char> >,struct std::hash<unsigned int>,struct std::equal_to<unsigned int>,class std::allocator<struct std::pair<unsigned int const ,class std::basic_string<char,struct std::char_traits<char>,class std::allocator<char> > > > > Hazel::OpenGLShader::PreProcess(const class std::basic_string<char,struct std::char_traits<char>,class std::allocator<char> > &)","ph":"X","pid":0,"tid":7944,"ts":1464614823344.600},{"cat":"function","dur":12626,"name":"Hazel::OpenGLShader::OpenGLShader(const class std::basic_string<char,struct std::char_traits<char>,class std::allocator<char> > &)","ph":"X","pid":0,"tid":7944,"ts":1464614823110.800},{"cat":"function","dur":111,"name":"class std::basic_string<char,struct std::char_traits<char>,class std::allocator<char> > Hazel::OpenGLShader::ReadFile(const class std::basic_string<char,struct std::char_traits<char>,class std::allocator<char> > &)","ph":"X","pid":0,"tid":7944,"ts":1464614835886.800},{"cat":"function","dur":42,"name":"class std::unordered_map<unsigned int,class std::basic_string<char,struct std::char_traits<char>,class std::allocator<char> >,struct std::hash<unsigned int>,struct std::equal_to<unsigned int>,class std::allocator<struct std::pair<unsigned int const ,class std::basic_string<char,struct std::char_traits<char>,class std::allocator<char> > > > > Hazel::OpenGLShader::PreProcess(const class std::basic_string<char,struct std::char_traits<char>,class std::allocator<char> > &)","ph":"X","pid":0,"tid":7944,"ts":1464614836046.500},{"cat":"function","dur":19984,"name":"Hazel::OpenGLShader::OpenGLShader(const class std::basic_string<char,struct std::char_traits<char>,class std::allocator<char> > &)","ph":"X","pid":0,"tid":7944,"ts":1464614835852.100},{"cat":"function","dur":54243,"name":"void Hazel::Renderer2D::Init(void)","ph":"X","pid":0,"tid":7944,"ts":1464614801742.900},{"cat":"function","dur":54360,"name":"void Hazel::Renderer::Init(void)","ph":"X","pid":0,"tid":7944,"ts":1464614801664.200},{"cat":"function","dur":605,"name":"void Hazel::ImGuiLayer::OnAttach(void)","ph":"X","pid":0,"tid":7944,"ts":1464614856088.500},{"cat":"function","dur":667,"name":"void Hazel::Application::PushOverlay(class Hazel::Layer *)","ph":"X","pid":0,"tid":7944,"ts":1464614856075.600},{"cat":"function","dur":504217,"name":"Hazel::Application::Application(const class std::basic_string<char,struct std::char_traits<char>,class std::allocator<char> > &,struct Hazel::ApplicationCommandLineArgs)","ph":"X","pid":0,"tid":7944,"ts":1464614352559.600},{"cat":"function","dur":10,"name":"Hazel::OrthographicCamera::OrthographicCamera(float,float,float,float)","ph":"X","pid":0,"tid":7944,"ts":1464614856831.000},{"cat":"function","dur":6550,"name":"stbi_load - OpenGLTexture2D::OpenGLTexture2D(const std::string&)","ph":"X","pid":0,"tid":7944,"ts":1464614856895.500},{"cat":"function","dur":7409,"name":"Hazel::OpenGLTexture2D::OpenGLTexture2D(const class std::basic_string<char,struct std::char_traits<char>,class std::allocator<char> > &)","ph":"X","pid":0,"tid":7944,"ts":1464614856894.900},{"cat":"function","dur":22774,"name":"stbi_load - OpenGLTexture2D::OpenGLTexture2D(const std::string&)","ph":"X","pid":0,"tid":7944,"ts":1464614864371.800},{"cat":"function","dur":23588,"name":"Hazel::OpenGLTexture2D::OpenGLTexture2D(const class std::basic_string<char,struct std::char_traits<char>,class std::allocator<char> > &)","ph":"X","pid":0,"tid":7944,"ts":1464614864371.300},{"cat":"function","dur":196,"name":"stbi_load - OpenGLTexture2D::OpenGLTexture2D(const std::string&)","ph":"X","pid":0,"tid":7944,"ts":1464614888042.500},{"cat":"function","dur":603,"name":"Hazel::OpenGLTexture2D::OpenGLTexture2D(const class std::basic_string<char,struct std::char_traits<char>,class std::allocator<char> > &)","ph":"X","pid":0,"tid":7944,"ts":1464614888042.100},{"cat":"function","dur":192,"name":"stbi_load - OpenGLTexture2D::OpenGLTexture2D(const std::string&)","ph":"X","pid":0,"tid":7944,"ts":1464614888708.500},{"cat":"function","dur":365,"name":"Hazel::OpenGLTexture2D::OpenGLTexture2D(const class std::basic_string<char,struct std::char_traits<char>,class std::allocator<char> > &)","ph":"X","pid":0,"tid":7944,"ts":1464614888708.100},{"cat":"function","dur":124,"name":"stbi_load - OpenGLTexture2D::OpenGLTexture2D(const std::string&)","ph":"X","pid":0,"tid":7944,"ts":1464614889131.300},{"cat":"function","dur":280,"name":"Hazel::OpenGLTexture2D::OpenGLTexture2D(const class std::basic_string<char,struct std::char_traits<char>,class std::allocator<char> > &)","ph":"X","pid":0,"tid":7944,"ts":1464614889131.000},{"cat":"function","dur":2712,"name":"void Hazel::EditorLayer::OnAttach(void)","ph":"X","pid":0,"tid":7944,"ts":1464614888035.600},{"cat":"function","dur":2786,"name":"void Hazel::Application::PushLayer(class Hazel::Layer *)","ph":"X","pid":0,"tid":7944,"ts":1464614888024.600}]}